README.rst
setup.py
filehub/__init__.py
filehub/resources.py
filehub/ui.html
filehub.egg-info/PKG-INFO
filehub.egg-info/SOURCES.txt
filehub.egg-info/dependency_links.txt
filehub.egg-info/entry_points.txt
filehub.egg-info/not-zip-safe
filehub.egg-info/requires.txt
filehub.egg-info/top_level.txt