Metadata-Version: 1.1
Name: filehub
Version: 0.1.3
Summary: A relay server for sharing files via HTTP
Home-page: https://github.com/l04m33/filehub
Author: Kay Zheng
Author-email: l04m33@gmail.com
License: http://l04m33.mit-license.org/
Platform: UNKNOWN
Classifier: License :: OSI Approved :: MIT License
Classifier: Programming Language :: Python :: 3.4
